zynapse10/__init__.py
zynapse10/cli.py
zynapse10-0.1.0.dist-info/METADATA
zynapse10-0.1.0.dist-info/WHEEL
zynapse10-0.1.0.dist-info/entry_points.txt
zynapse10-0.1.0.dist-info/top_level.txt
zynapse10-0.1.0.dist-info/RECORD
