Metadata-Version: 2.4
Name: zynapse10
Version: 0.1.0
Summary: CLI للتفاعل مع Gemini AI من الطرفية
Author-email: Your Name <you@example.com>
License: MIT
Requires-Python: >=3.7
